NowCoder-Verilog/BasicLanguage/VL7求两个数的差值.v
`timescale 1ns/1ns
module data_minus(
	input clk,
	input rst_n,
	input [7:0]a,
	input [7:0]b,

	output  reg [8:0]c
);

    always @(posedge clk, negedge rst_n)
        begin
            if (!rst_n) begin c<=0;end
            else begin
                c<=(a>b)?(a-b):(b-a);
            end
        end

endmodule

module testbench();
	reg signed [7:0] a,b;
	reg clk,rst_n;
	wire signed [8:0]c;

    always #005 clk<=~clk;

    initial begin
        #000 clk = 0; rst_n = 0;
        #010 rst_n = 1;
        #020 a=8'b10101010;b=8'b01010101;
        #020 a=8'b00001010;b=8'b11010101;
        #020 a=8'b11111010;b=8'b01010100;
        #020 a=8'b11111010;b=8'b11000000;
        $stop;
    end

    initial begin
        $dumpfile("out.vcd");
        $dumpvars(0,testbench);
    end

    data_minus dut(
        .clk(clk),
        .rst_n(rst_n),
        .a(a),
        .b(b),
        .c(c)
    );

endmodule

out.vcd
$date
	Tue Jul 26 23:31:37 2022
$end
$version
	ModelSim Version 10.7
$end
$timescale
	1ns
$end

$scope module testbench $end
$var reg 8 ! a [7:0] $end
$var reg 8 " b [7:0] $end
$var reg 1 # clk $end
$var reg 1 $ rst_n $end
$var wire 1 % c [8] $end
$var wire 1 & c [7] $end
$var wire 1 ' c [6] $end
$var wire 1 ( c [5] $end
$var wire 1 ) c [4] $end
$var wire 1 * c [3] $end
$var wire 1 + c [2] $end
$var wire 1 , c [1] $end
$var wire 1 - c [0] $end

$scope module dut $end
$var wire 1 . clk $end
$var wire 1 / rst_n $end
$var wire 1 0 a [7] $end
$var wire 1 1 a [6] $end
$var wire 1 2 a [5] $end
$var wire 1 3 a [4] $end
$var wire 1 4 a [3] $end
$var wire 1 5 a [2] $end
$var wire 1 6 a [1] $end
$var wire 1 7 a [0] $end
$var wire 1 8 b [7] $end
$var wire 1 9 b [6] $end
$var wire 1 : b [5] $end
$var wire 1 ; b [4] $end
$var wire 1 < b [3] $end
$var wire 1 = b [2] $end
$var wire 1 > b [1] $end
$var wire 1 ? b [0] $end
$var reg 9 @ c [8:0] $end
$upscope $end
$upscope $end
$enddefinitions $end
#0
$dumpvars
bx !
bx "
0#
0$
b0 @
0-
0,
0+
0*
0)
0(
0'
0&
0%
x?
x>
x=
x<
x;
x:
x9
x8
x7
x6
x5
x4
x3
x2
x1
x0
0/
0.
$end
#5
1#
1.
#10
1$
1/
0#
0.
#15
1#
1.
bx @
x-
x,
x+
x*
x)
x(
x'
x&
x%
#20
0#
0.
#25
1#
1.
#30
b10101010 !
b1010101 "
1?
0>
1=
0<
1;
0:
19
08
07
16
05
14
03
12
01
10
0#
0.
#35
1#
1.
b1010101 @
1-
0,
1+
0*
1)
0(
1'
0&
0%
#40
0#
0.
#45
1#
1.
#50
b1010 !
b11010101 "
18
02
00
0#
0.
#55
1#
1.
b11001011 @
1,
0+
1*
0)
1&
#60
0#
0.
#65
1#
1.
#70
b11111010 !
b1010100 "
0?
08
13
12
11
10
0#
0.
#75
1#
1.
b10100110 @
0-
1+
0*
1(
0'
#80
0#
0.
#85
1#
1.
#90
b11000000 "
